{
  "version": "0.3.14-fixed",
  "steps": [
    {
      "tag": "CreateField",
      "model": "target",
      "field": "protocol",
      "type": "protocol",
      "arity": "List"
    },
    {
      "tag": "CreateField",
      "model": "protocol",
      "field": "server_id",
      "type": "String",
      "arity": "Required"
    },
    {
      "tag": "CreateField",
      "model": "protocol",
      "field": "target",
      "type": "target",
      "arity": "Optional"
    },
    {
      "tag": "CreateDirective",
      "location": {
        "path": {
          "tag": "Field",
          "model": "protocol",
          "field": "target"
        },
        "directive": "relation"
      }
    },
    {
      "tag": "CreateArgument",
      "location": {
        "tag": "Directive",
        "path": {
          "tag": "Field",
          "model": "protocol",
          "field": "target"
        },
        "directive": "relation"
      },
      "argument": "fields",
      "value": "[targetId]"
    },
    {
      "tag": "CreateArgument",
      "location": {
        "tag": "Directive",
        "path": {
          "tag": "Field",
          "model": "protocol",
          "field": "target"
        },
        "directive": "relation"
      },
      "argument": "references",
      "value": "[id]"
    },
    {
      "tag": "CreateField",
      "model": "protocol",
      "field": "targetId",
      "type": "String",
      "arity": "Optional"
    },
    {
      "tag": "UpdateField",
      "model": "protocol",
      "field": "server",
      "arity": "Required"
    },
    {
      "tag": "CreateDirective",
      "location": {
        "path": {
          "tag": "Field",
          "model": "protocol",
          "field": "server"
        },
        "directive": "relation"
      }
    },
    {
      "tag": "CreateArgument",
      "location": {
        "tag": "Directive",
        "path": {
          "tag": "Field",
          "model": "protocol",
          "field": "server"
        },
        "directive": "relation"
      },
      "argument": "fields",
      "value": "[server_id]"
    },
    {
      "tag": "CreateArgument",
      "location": {
        "tag": "Directive",
        "path": {
          "tag": "Field",
          "model": "protocol",
          "field": "server"
        },
        "directive": "relation"
      },
      "argument": "references",
      "value": "[id]"
    }
  ]
}